PicoAutonomousRobotics.py
KitronikPicoAutonomousRoboticsPlatform-1.0.0.dist-info/LICENSE
KitronikPicoAutonomousRoboticsPlatform-1.0.0.dist-info/METADATA
KitronikPicoAutonomousRoboticsPlatform-1.0.0.dist-info/WHEEL
KitronikPicoAutonomousRoboticsPlatform-1.0.0.dist-info/top_level.txt
KitronikPicoAutonomousRoboticsPlatform-1.0.0.dist-info/RECORD
