Metadata-Version: 2.1
Name: KitronikPicoAutonomousRoboticsPlatform
Version: 1.0.0
Summary: Kitronik Autonomous Robotics Platform (Buggy) for Pico
License-File: LICENSE
